LICENSE
MANIFEST.in
README.md
pyproject.toml
setup.cfg
setup.py
django_email_certify.egg-info/PKG-INFO
django_email_certify.egg-info/SOURCES.txt
django_email_certify.egg-info/dependency_links.txt
django_email_certify.egg-info/requires.txt
django_email_certify.egg-info/top_level.txt
email_verification/__init__.py
email_verification/admin.py
email_verification/apps.py
email_verification/models.py
email_verification/tests.py
email_verification/urls.py
email_verification/views.py
email_verification/migrations/0001_initial.py
email_verification/migrations/0002_remove_token_valid.py
email_verification/migrations/__init__.py
email_verification/templates/email_verification/mail.html
email_verification/templates/email_verification/pre-login-failure.html
email_verification/templates/email_verification/pre-login-success.html