Metadata-Version: 2.1
Name: django-email-certify
Version: 1.0
Summary: A Django package to manage user email verification on registration
Home-page: https://github.com/codewitgabi/django-email-certify
Author: Gabriel Michael Ojomakpene (codewitgabi)
Author-email: codewitgabi222@gmail.com
License: MIT-License
Classifier: Environment :: Web Environment
Classifier: Framework :: Django
Classifier: Framework :: Django :: 3.2
Classifier: Intended Audience :: Developers
Classifier: License :: OSI Approved :: BSD License
Classifier: Operating System :: OS Independent
Classifier: Programming Language :: Python
Classifier: Programming Language :: Python :: 3
Classifier: Programming Language :: Python :: 3 :: Only
Classifier: Programming Language :: Python :: 3.8
Classifier: Programming Language :: Python :: 3.9
Classifier: Topic :: Internet :: WWW/HTTP
Classifier: Topic :: Internet :: WWW/HTTP :: Dynamic Content
Requires-Python: >=3.8
License-File: LICENSE
